nlppets/__init__.py
nlppets/datasets/__init__.py
nlppets/datasets/builders/__init__.py
nlppets/datasets/builders/raw_text.py
nlppets/general/__init__.py
nlppets/general/add_subtoken_symbol.py
nlppets/general/dir_to_sentence.py
nlppets/general/extract_chinese_token.py
nlppets/general/file_to_sentence.py
nlppets/general/is_chinese_token.py
nlppets/general/monkey_patch.py
nlppets/general/split_chinese_token.py
nlppets/general/split_sentence.py
nlppets/torch/__init__.py
nlppets/torch/calculate_gradient_accumulation.py
nlppets/torch/combine_model.py
nlppets/torch/concat_linear.py
nlppets/torch/count_cuda_devices.py
nlppets/torch/count_parameters.py
nlppets/torch/freeze_tensor.py
nlppets/torch/replace_module.py
nlppets/torch/to_device.py
nlppets/transformers/__init__.py
nlppets/transformers/model/__init__.py
nlppets/transformers/model/bert/__init__.py
nlppets/transformers/model/bert/adapter.py
nlppets/transformers/model/bert/domain_enhance_att.py
nlppets/transformers/model/bert/domain_enhance_ffn.py
nlppets/transformers/model/bloom/__init__.py
nlppets/transformers/model/bloom/domain_enhance_att.py
nlppets/transformers/model/bloom/domain_enhance_ffn.py
nlppets/transformers/model/chatglm/__init__.py
nlppets/transformers/model/chatglm/domain_enhance_att.py
nlppets/transformers/model/chatglm/domain_enhance_ffn.py
nlppets/transformers/model/llama/__init__.py
nlppets/transformers/model/llama/domain_enhance_ffn.py
nlppets/transformers/tokenize/__init__.py
nlppets/transformers/tokenize/chinese_wwm.py
nlppets/transformers/tokenize/extract_subtoken_indexs.py
nlppets/transformers/trainer/__init__.py
nlppets/transformers/trainer/clm.py
nlppets/transformers/trainer/mlm.py
nlppets-0.1.0.dist-info/LICENSE
nlppets-0.1.0.dist-info/METADATA
nlppets-0.1.0.dist-info/WHEEL
nlppets-0.1.0.dist-info/RECORD
